LICENSE
MANIFEST.in
README.md
README.rst
requirements.txt
setup.py
docs/LivePreview.gif
livepreview/__init__.py
livepreview/apps.py
livepreview/models.py
livepreview/views.py
livepreview/wagtail_hooks.py
livepreview/migrations/0001_initial.py
livepreview/migrations/__init__.py
livepreview/static/.DS_Store
livepreview/static/livepreview/.DS_Store
livepreview/static/livepreview/css/livepreview.css
livepreview/static/livepreview/images/loader.gif
livepreview/static/livepreview/js/jquery-3.4.1.min.js
livepreview/static/livepreview/js/livepreview.js
livepreview/static/livepreview/js/livepreview_fe.js
livepreview/static/livepreview/js/split.min.js
livepreview/templates/livepreview_javascript_tags.html
livepreview/templates/wagtailadmin/edit_handlers/tabbed_interface.html
livepreview/templates/wagtailadmin/pages/edit.html
livepreview/templatetags/livepreview_tags.py
wagtail_livepreview.egg-info/PKG-INFO
wagtail_livepreview.egg-info/SOURCES.txt
wagtail_livepreview.egg-info/dependency_links.txt
wagtail_livepreview.egg-info/top_level.txt