Metadata-Version: 1.1
Name: wagtail-livepreview
Version: 0.1
Summary: Live preview your page changes as you make them.
Home-page: https://github.com/KalobTaulien/wagtail-livepreview
Author: Kalob Taulien
Author-email: kalob@learnwagtail.com
License: BSD
Platform: UNKNOWN
Classifier: Environment :: Web Environment
Classifier: Framework :: Django
Classifier: Framework :: Django :: 2.2
Classifier: Framework :: Wagtail
Classifier: Framework :: Wagtail :: 2
Classifier: Intended Audience :: Developers
Classifier: License :: OSI Approved :: BSD License
Classifier: Operating System :: OS Independent
Classifier: Programming Language :: Python
Classifier: Programming Language :: Python :: 3.5
Classifier: Programming Language :: Python :: 3.6
Classifier: Topic :: Internet :: WWW/HTTP
Classifier: Topic :: Internet :: WWW/HTTP :: Dynamic Content
